Metadata-Version: 2.1
Name: tinybot
Version: 1.0.0
Summary: Very simple yet flexible Telegram Bot API
Home-page: http://github.com/necauqua/tinybot
Author: Anton Bulakh
Author-email: necauqua@gmail.com
License: MIT
Download-URL: https://github.com/necauqua/tinybot/archive/v1.0.0.tar.gz
Keywords: telegram,bot,api
Platform: UNKNOWN
Classifier: Development Status :: 5 - Production/Stable
Classifier: Environment :: Console
Classifier: Environment :: Web Environment
Classifier: Intended Audience :: Developers
Classifier: License :: OSI Approved :: MIT License
Classifier: Programming Language :: Python :: 3
Classifier: Topic :: Communications :: Chat
Classifier: Topic :: Utilities
